pyVRL-0.0.2.dist-info/METADATA
pyVRL-0.0.2.dist-info/WHEEL
pyVRL-0.0.2.dist-info/license_files/LICENSE
pyvrl/__init__.py
pyvrl/pyvrl.cpython-310-arm-linux-gnueabihf.so
pyVRL-0.0.2.dist-info/RECORD
