Metadata-Version: 2.3
Name: pyVRL
Version: 0.0.2
Classifier: Programming Language :: Rust
Classifier: Programming Language :: Python :: Implementation :: CPython
Classifier: Programming Language :: Python :: Implementation :: PyPy
Classifier: License :: OSI Approved :: MIT License
License-File: LICENSE
Summary: Exposes Vector VRL to Python
Author-email: "Crowdalert, Inc" <hello@crowdalert.com>
Requires-Python: >=3.10
Project-URL: Homepage, https://github.com/crowdalert/pyvrl
